setup.py
django_rest_framework_proxy.egg-info/PKG-INFO
django_rest_framework_proxy.egg-info/SOURCES.txt
django_rest_framework_proxy.egg-info/dependency_links.txt
django_rest_framework_proxy.egg-info/requires.txt
django_rest_framework_proxy.egg-info/top_level.txt
rest_framework_proxy/__init__.py
rest_framework_proxy/adapters.py
rest_framework_proxy/models.py
rest_framework_proxy/settings.py
rest_framework_proxy/utils.py
rest_framework_proxy/views.py